ahps_alerts/__init__.py
ahps_alerts/ahps_alerts.py
ahps_alerts/cli.py
ahps_alerts-0.1.5.dist-info/DESCRIPTION.rst
ahps_alerts-0.1.5.dist-info/METADATA
ahps_alerts-0.1.5.dist-info/RECORD
ahps_alerts-0.1.5.dist-info/WHEEL
ahps_alerts-0.1.5.dist-info/entry_points.txt
ahps_alerts-0.1.5.dist-info/metadata.json
ahps_alerts-0.1.5.dist-info/top_level.txt
