Metadata-Version: 2.0
Name: ahps-alerts
Version: 0.1.5
Summary: Retrieve NWS AHPS alerts
Home-page: https://github.com/DavidHickman/ahps_alerts
Author: David Hickman
Author-email: david.hickman@twdb.texas.gov
License: MIT license
Keywords: ahps_alerts,National Weather Service,TNRIS,Texas
Platform: UNKNOWN
Classifier: Development Status :: 2 - Pre-Alpha
Classifier: Intended Audience :: Developers
Classifier: License :: OSI Approved :: MIT License
Classifier: Natural Language :: English
Classifier: Programming Language :: Python :: 2
Classifier: Programming Language :: Python :: 2.6
Classifier: Programming Language :: Python :: 2.7
Classifier: Programming Language :: Python :: 3
Classifier: Programming Language :: Python :: 3.3
Classifier: Programming Language :: Python :: 3.4
Classifier: Programming Language :: Python :: 3.5
Requires-Dist: Click (>=6.0)
Requires-Dist: beautifulsoup4
Requires-Dist: feedparser
